py_sampquery-0.0.6.dist-info/licenses/AUTHORS.md
py_sampquery-0.0.6.dist-info/licenses/LICENSE
sampquery/__init__.py
sampquery/client.py
sampquery/exceptions.py
sampquery/player.py
sampquery/py.typed
sampquery/rule.py
sampquery/server.py
sampquery/utils.py
py_sampquery-0.0.6.dist-info/METADATA
py_sampquery-0.0.6.dist-info/WHEEL
py_sampquery-0.0.6.dist-info/top_level.txt
py_sampquery-0.0.6.dist-info/RECORD
